nomad_camels_driver_openCV_instrument/__init__.py
nomad_camels_driver_openCV_instrument/openCV_instrument.py
nomad_camels_driver_openCV_instrument/openCV_instrument_ophyd.py
nomad_camels_driver_opencv_instrument-0.1.2.dist-info/licenses/LICENSE
nomad_camels_driver_opencv_instrument-0.1.2.dist-info/METADATA
nomad_camels_driver_opencv_instrument-0.1.2.dist-info/WHEEL
nomad_camels_driver_opencv_instrument-0.1.2.dist-info/top_level.txt
nomad_camels_driver_opencv_instrument-0.1.2.dist-info/RECORD
